hashes/__main__.py
hashes/__init__.py
hashes/ops/ldap_sha1.py
hashes/ops/msdcc.py
hashes/ops/cisco_pix.py
hashes/ops/bcrypt.py
hashes/ops/ldap_md5.py
hashes/ops/nt.py
hashes/ops/postgres_md5.py
hashes/ops/sha256_crypt.py
hashes/ops/mysql41.py
hashes/ops/sha256.py
hashes/ops/sha1.py
hashes/ops/cisco_type7.py
hashes/ops/md5_crypt.py
hashes/ops/msdcc2.py
hashes/ops/ldap_salted_sha1.py
hashes/ops/oracle10.py
hashes/ops/sha512_crypt.py
hashes/ops/mysql323.py
hashes/ops/sha512.py
hashes/ops/ldap_salted_md5.py
hashes/ops/mssql2005.py
hashes/ops/oracle11.py
hashes/ops/md5.py
hashes/ops/__init__.py
hashes/ops/mssql2000.py
hashes/ops/sha1_crypt.py
hashes/common/orchestra.py
hashes/common/helpers.py
hashes/common/__init__.py
hashes-1.1.0.dist-info/top_level.txt
hashes-1.1.0.dist-info/METADATA
hashes-1.1.0.dist-info/WHEEL
hashes-1.1.0.dist-info/metadata.json
hashes-1.1.0.dist-info/RECORD
hashes-1.1.0.dist-info/entry_points.txt
hashes-1.1.0.dist-info/zip-safe
hashes-1.1.0.dist-info/DESCRIPTION.rst
